deepflow/Geometry.py
deepflow/__init__.py
deepflow/domain.py
deepflow/evaluation.py
deepflow/neuralnetwork.py
deepflow/pde.py
deepflow/physicsinformed.py
deepflow/utility.py
deepflow/visualization.py
deepflow-0.1.1.dist-info/licenses/LICENSE
deepflow-0.1.1.dist-info/METADATA
deepflow-0.1.1.dist-info/WHEEL
deepflow-0.1.1.dist-info/top_level.txt
deepflow-0.1.1.dist-info/RECORD
