Metadata-Version: 2.4
Name: deepflow
Version: 0.1.1
Summary: Physics-Informed Neural Networks for Fluid Dynamics
Author-email: Thammatorn Jamraschai <thammatorn.j@gmail.com>
License-Expression: MIT
Project-URL: Homepage, https://github.com/YoYo-XYZ/deepflow
Keywords: PINNs,neural-networks,fluid-dynamics,PDEs,physics-informed,deep-learning
Requires-Python: >=3.8
License-File: LICENSE
Requires-Dist: torch>=1.7.0
Requires-Dist: numpy>=1.19.0
Requires-Dist: matplotlib>=3.3.0
Requires-Dist: sympy>=1.5.0
Dynamic: license-file
